api/__init__.py
api/endpoints.py
api/schema.py
auth/__init__.py
auth/authenticator.py
auth/authfactory.py
auth/aws/__init__.py
auth/aws/awsecr.py
auth/basic/__init__.py
auth/basic/basicauth.py
auth/creds/__init__.py
auth/creds/cred_errors.py
auth/creds/credbuilder.py
db/__init__.py
db/job_log.py
jobs/__init__.py
jobs/runner.py
log/__init__.py
log/log_manager.py
models/__init__.py
models/runner_cfg.py
swarmer/__init__.py
swarmer/swarmer.py
swarmer-0.5.0.dist-info/LICENSE
swarmer-0.5.0.dist-info/METADATA
swarmer-0.5.0.dist-info/WHEEL
swarmer-0.5.0.dist-info/entry_points.txt
swarmer-0.5.0.dist-info/top_level.txt
swarmer-0.5.0.dist-info/RECORD
