Metadata-Version: 2.1
Name: swarmer
Version: 0.5.0
Summary: Docker Swarm One-Shot Service Runner
Home-page: https://github.com/stevepentland/swarmer
Author: Steve Pentland
Author-email: swarmerproject@outlook.com
License: MIT
Keywords: docker swarm
Platform: UNKNOWN
Classifier: Programming Language :: Python :: 3.6
Classifier: Programming Language :: Python :: 3.7
Classifier: License :: OSI Approved :: MIT License
Classifier: Operating System :: POSIX :: Linux
Classifier: Development Status :: 4 - Beta
Classifier: Environment :: Console
Classifier: Intended Audience :: Developers
Classifier: Natural Language :: English
Classifier: Topic :: System :: Distributed Computing
Classifier: Topic :: Utilities
Requires-Python: >=3.6, <4
Requires-Dist: redis (==2.10.6)
Requires-Dist: falcon (==1.4.1)
Requires-Dist: docker (==3.5.1)
Requires-Dist: docker-pycreds (==0.3.0)
Requires-Dist: ulid-py (==0.0.7)
Requires-Dist: requests (==2.20.0)
Requires-Dist: gunicorn (==19.9.0)
Requires-Dist: jsonschema (==2.6.0)
Provides-Extra: aws
Requires-Dist: boto3 (<1.10,>=1.9) ; extra == 'aws'
